geolocate/__init__.py
geolocate/constants.py
geolocate/engines.py
geolocate/exceptions.py
geolocate/exports.py
geolocate/utils.py
geolocate-0.1.2.dist-info/LICENSE
geolocate-0.1.2.dist-info/WHEEL
geolocate-0.1.2.dist-info/METADATA
geolocate-0.1.2.dist-info/RECORD
