Metadata-Version: 2.1
Name: geolocate
Version: 0.1.2
Summary: Georeferencing large amounts of data for free.
Home-page: https://github.com/gabriel-milan/geolocate
License: GPL-3.0-only
Keywords: geocode,geolocate,georeferencing
Author: Gabriel Gazola Milan
Author-email: gabriel.gazola@poli.ufrj.br
Requires-Python: >=3.7,<4.0
Classifier: Development Status :: 4 - Beta
Classifier: License :: OSI Approved :: GNU General Public License v3 (GPLv3)
Classifier: Programming Language :: Python :: 3
Classifier: Programming Language :: Python :: 3.7
Classifier: Programming Language :: Python :: 3.8
Classifier: Programming Language :: Python :: 3.9
Classifier: Programming Language :: Python :: 3.10
Classifier: Programming Language :: Python :: 3.11
Requires-Dist: p-tqdm (>=1.3.3,<2.0.0)
Requires-Dist: requests (>=2.20,<3.0)
Project-URL: Repository, https://github.com/gabriel-milan/geolocate
